visplotlib_test
