Metadata-Version: 2.1
Name: visplotlib-test
Version: 0.2.1
Summary: Extensions to Matplotlib and Seaborn plotting for Visium SA.
Home-page: https://github.com/yetiiil/visplotlib_test
Author: Visium SA
Author-email: yuxiao.li@visium.ch
Classifier: Programming Language :: Python :: 3
Classifier: License :: OSI Approved :: MIT License
Classifier: Operating System :: OS Independent
License-File: LICENSE
